hnswlib.cpython-310-darwin.so
hnswlib_embedinai-0.7.1.dist-info/LICENSE
hnswlib_embedinai-0.7.1.dist-info/METADATA
hnswlib_embedinai-0.7.1.dist-info/WHEEL
hnswlib_embedinai-0.7.1.dist-info/top_level.txt
hnswlib_embedinai-0.7.1.dist-info/RECORD
